obplanner/__init__.py
obplanner/main.py
obplanner/model/__init__.py
obplanner/model/build.py
obplanner/model/layer_default.py
obplanner/model/pattern.py
obplanner/model/single_file.py
obplanner/model/strategies.py
obplanner/obf/__init__.py
obplanner/obf/generate_obf.py
obplanner/obf/helpers/__init__.py
obplanner/obf/helpers/build.lua
obplanner/obf/helpers/buildProcessors.json
obplanner/obf/helpers/dependencies.json
obplanner/obf/helpers/manifest.json
obplanner/obf/helpers/obpviewer.py
obplanner/pattern/__init__.py
obplanner/pattern/compensator.py
obplanner/pattern/generator.py
obplanner/strategy/__init__.py
obplanner/strategy/generate_strategy.py
obplanner/strategy/strategy_mapping.py
obplanner/strategy/helpers/__init__.py
obplanner/strategy/helpers/find_connected.py
obplanner/strategy/helpers/find_contours.py
obplanner/strategy/helpers/offset_pattern.py
obplanner/strategy/sort_strategies/__init__.py
obplanner/strategy/sort_strategies/contour_sorting.py
obplanner/strategy/sort_strategies/line_sorting.py
obplanner/strategy/sort_strategies/spot_sorting.py
obplanner-0.0.6.dist-info/licenses/LICENSE
obplanner-0.0.6.dist-info/METADATA
obplanner-0.0.6.dist-info/WHEEL
obplanner-0.0.6.dist-info/top_level.txt
obplanner-0.0.6.dist-info/RECORD
